scalable/__init__.py
scalable/apps.py
scalable/models.py
django_scalable-0.0.1b1.dist-info/LICENSE
django_scalable-0.0.1b1.dist-info/METADATA
django_scalable-0.0.1b1.dist-info/WHEEL
django_scalable-0.0.1b1.dist-info/top_level.txt
django_scalable-0.0.1b1.dist-info/RECORD
